energyplus_iddidf/__init__.py
energyplus_iddidf/__main__.py
energyplus_iddidf/cli.py
energyplus_iddidf/exceptions.py
energyplus_iddidf/idd_objects.py
energyplus_iddidf/idd_processor.py
energyplus_iddidf/idf_objects.py
energyplus_iddidf/idf_processor.py
energyplus_iddidf/settings.py
energyplus_idd_idf_utilities-0.88.dist-info/LICENSE.txt
energyplus_idd_idf_utilities-0.88.dist-info/METADATA
energyplus_idd_idf_utilities-0.88.dist-info/WHEEL
energyplus_idd_idf_utilities-0.88.dist-info/entry_points.txt
energyplus_idd_idf_utilities-0.88.dist-info/top_level.txt
energyplus_idd_idf_utilities-0.88.dist-info/RECORD
