Metadata-Version: 2.1
Name: energyplus-idd-idf-utilities
Version: 0.88
Summary: EnergyPlus idd/idf manipulation in Python.
Home-page: https://github.com/myoldmopar/py-idd-idf
Author: Edwin Lee, for NREL, for the United States Department of Energy
License: ModifiedBSD
Keywords: energyplus_launch,ep_launch,EnergyPlus,eplus,Energy+,Building Simulation,Whole Building Energy Simulation,Heat Transfer,HVAC,Modeling
Platform: Linux (Tested on Ubuntu)
Platform: MacOSX
Platform: Windows
Classifier: Development Status :: 4 - Beta
Classifier: Intended Audience :: Science/Research
Classifier: Intended Audience :: Developers
Classifier: Natural Language :: English
Classifier: Operating System :: OS Independent
Classifier: Programming Language :: Python :: 3 :: Only
Classifier: Topic :: Scientific/Engineering
Classifier: Topic :: Scientific/Engineering :: Physics
Classifier: Topic :: Utilities
